FlowAnalyzer/FlowAnalyzer.py
FlowAnalyzer/Models.py
FlowAnalyzer/PacketParser.py
FlowAnalyzer/Path.py
FlowAnalyzer/__init__.py
FlowAnalyzer/logging_config.py
flowanalyzer-0.4.4.dist-info/licenses/LICENSE
flowanalyzer-0.4.4.dist-info/METADATA
flowanalyzer-0.4.4.dist-info/WHEEL
flowanalyzer-0.4.4.dist-info/top_level.txt
flowanalyzer-0.4.4.dist-info/RECORD
