Metadata-Version: 2.4
Name: FlowAnalyzer
Version: 0.4.4
Summary: FlowAnalyzer是一个流量分析器，用于解析和处理tshark导出的JSON数据文件
Home-page: https://github.com/Byxs20/FlowAnalyzer
Author: Byxs20
Author-email: 97766819@qq.com
Classifier: Development Status :: 3 - Alpha
Classifier: Intended Audience :: Developers
Classifier: License :: OSI Approved :: MIT License
Classifier: Programming Language :: Python :: 3
Classifier: Programming Language :: Python :: 3.6
Classifier: Programming Language :: Python :: 3.7
Classifier: Programming Language :: Python :: 3.8
Classifier: Programming Language :: Python :: 3.9
License-File: LICENSE
Dynamic: author
Dynamic: author-email
Dynamic: classifier
Dynamic: description
Dynamic: description-content-type
Dynamic: home-page
Dynamic: license-file
Dynamic: summary
